{
  "ticker": "PG",
  "target_date": "2025-08-11",
  "actual_date": "2025-08-11",
  "collected_at": "2025-12-08T12:07:37.389206",
  "price": {
    "open": 152.47,
    "high": 154.31,
    "low": 152.25,
    "close": 153.9037628173828,
    "volume": 7331700,
    "change_1d_pct": 0.96,
    "change_7d_pct": 3.0,
    "change_30d_pct": -2.39
  },
  "technicals": {
    "rsi_14": 38.0,
    "sma_20": 153.26,
    "sma_50": 156.61,
    "macd": -1.255,
    "macd_signal": -1.411,
    "macd_histogram": 0.156,
    "bb_upper": 158.9,
    "bb_lower": 147.62,
    "price_vs_sma20_pct": 0.42,
    "price_vs_sma50_pct": -1.73,
    "volume_ratio": 0.95
  },
  "fundamentals": {
    "market_cap": 327043055616,
    "pe_ratio": 20.369242,
    "forward_pe": 18.831942,
    "price_to_book": 6.2194777,
    "price_to_sales": 3.8506005,
    "profit_margin": 19.74,
    "operating_margin": 27.58,
    "roe": 31.9,
    "roa": 10.75,
    "revenue_growth": 3.0,
    "earnings_growth": 21.4,
    "debt_to_equity": 67.125,
    "current_ratio": 0.714,
    "quick_ratio": 0.465,
    "dividend_yield": 295.0,
    "fifty_two_week_high": 179.99,
    "fifty_two_week_low": 139.21,
    "fifty_day_avg": 149.197,
    "two_hundred_day_avg": 158.58435,
    "analyst_target": 168.95454,
    "analyst_recommendation": "buy",
    "num_analysts": 22,
    "sector": "Consumer Defensive",
    "industry": "Household & Personal Products",
    "pct_from_52w_high": -22.37,
    "pct_from_52w_low": 0.38
  },
  "macro": {
    "spy": {
      "price": 634.16,
      "change_1d_pct": -0.2,
      "change_7d_pct": 2.28
    },
    "vix": {
      "level": 16.25,
      "signal": "NORMAL"
    },
    "treasury_10y": {
      "yield_pct": 4.27
    },
    "dollar_index": {
      "level": 98.52
    },
    "gold": {
      "price": 3353.1
    },
    "regime": "BULL_LOW_VOL"
  },
  "news": [
    {
      "headline": "New Downy\u00ae Gentle Soft + Fresh Debuts with Audio Romance Series, \"Almost Scandalously Soft Stories\"",
      "source": "Yahoo",
      "datetime": 1754913600,
      "summary": "CINCINNATI, August 11, 2025--Downy\u00ae, a trusted leader in laundry, announces the launch of Downy Gentle Soft + Fresh, a new fabric softener designed for consumers who want softness and scent without compromising on gentleness. Supporting the launch is an original audio campaign, \"Almost Scandalously ",
      "url": "https://finnhub.io/api/news?id=e4f01021a74145189cfba38df8cc91a8f0cb0ab986ee4c0f9f77370076a11985"
    },
    {
      "headline": "TD Cowen Maintains Buy on P&G (PG), Citing Innovation and Leadership Shift",
      "source": "Yahoo",
      "datetime": 1754798406,
      "summary": "The Procter & Gamble Company (NYSE:PG) is one of the best defensive stocks to invest in according to analysts. The company reported its Q4 2025 (FY ends in June) on July 29 with $84.3 billion in revenue and $6.83 in EPS. In fiscal 2025, the company delivered more than $16 billion in shareholder retu",
      "url": "https://finnhub.io/api/news?id=243a0789e9e2c10cb567d9b281b5bcf14810e524a4f7cd934ee7510d8a4e4f69"
    },
    {
      "headline": "3 Reasons PG is Risky and 1 Stock to Buy Instead",
      "source": "Yahoo",
      "datetime": 1754681987,
      "summary": "Over the past six months, Procter & Gamble\u2019s shares (currently trading at $153.55) have posted a disappointing 8.3% loss, well below the S&P 500\u2019s 5.3% gain. This may have investors wondering how to approach the situation.",
      "url": "https://finnhub.io/api/news?id=3b8438aa106a11a6e6fb20315a101d24366e2aec317d6e22665883cd5eeacb7e"
    },
    {
      "headline": "Dividend Champion, Contender, And Challenger Highlights: Week Of August 10",
      "source": "SeekingAlpha",
      "datetime": 1754676459,
      "summary": "A weekly summary of dividend activity for Dividend Champions, Contenders, and Challengers. Read the full list for the week of August 10, 2025 -- here on Seeking Alpha.",
      "url": "https://finnhub.io/api/news?id=d3328f7322da5e3893bf572815a85939fa978cabae6f64d3ced8fdd259c3dc94"
    },
    {
      "headline": "Saudi Arabia Household Cleaners Market Analysis Report 2025-2033 | Rise in Eco-Friendly Household Cleaners as Saudi Consumers Opt for Natural and Non-Toxic Products",
      "source": "Yahoo",
      "datetime": 1754660280,
      "summary": "The Saudi Arabia Household Cleaners Market is projected to grow from US$ 460.29 Million in 2024 to US$ 661.97 Million by 2033, at a CAGR of 4.12%. This growth is driven by increasing urbanization, a rising middle class, and greater awareness of health and cleanliness. Key segments include surface cl",
      "url": "https://finnhub.io/api/news?id=3cbacf206211a5b4067f6e2f91cab9bf9d238276a740707079e7f74dae37b7ff"
    }
  ],
  "news_count": 5,
  "sec_filings": [
    {
      "form": "4",
      "date": "2025-08-07",
      "description": "xslF345X05/form4.xml",
      "url": "https://www.sec.gov/Archives/edgar/data/80424/000008042425000105/xslF345X05/form4.xml"
    },
    {
      "form": "4",
      "date": "2025-08-07",
      "description": "xslF345X05/form4.xml",
      "url": "https://www.sec.gov/Archives/edgar/data/80424/000008042425000102/xslF345X05/form4.xml"
    },
    {
      "form": "4",
      "date": "2025-08-07",
      "description": "xslF345X05/form4.xml",
      "url": "https://www.sec.gov/Archives/edgar/data/80424/000008042425000101/xslF345X05/form4.xml"
    },
    {
      "form": "4",
      "date": "2025-08-07",
      "description": "xslF345X05/form4.xml",
      "url": "https://www.sec.gov/Archives/edgar/data/80424/000008042425000098/xslF345X05/form4.xml"
    },
    {
      "form": "4",
      "date": "2025-08-07",
      "description": "xslF345X05/form4.xml",
      "url": "https://www.sec.gov/Archives/edgar/data/80424/000008042425000097/xslF345X05/form4.xml"
    }
  ],
  "sec_filings_count": 5,
  "data_quality": {
    "has_price": true,
    "has_technicals": true,
    "has_fundamentals": true,
    "has_macro": true,
    "has_news": true,
    "has_sec_filings": true
  }
}