{
  "ticker": "CVX",
  "target_date": "2025-03-25",
  "actual_date": "2025-03-25",
  "collected_at": "2025-12-08T11:33:26.563567",
  "price": {
    "open": 160.48,
    "high": 162.16,
    "low": 159.55,
    "close": 160.34735107421875,
    "volume": 7869200,
    "change_1d_pct": 0.56,
    "change_7d_pct": 5.68,
    "change_30d_pct": 7.71
  },
  "technicals": {
    "rsi_14": 80.3,
    "sma_20": 152.42,
    "sma_50": 150.56,
    "macd": 2.838,
    "macd_signal": 1.848,
    "macd_histogram": 0.989,
    "bb_upper": 161.94,
    "bb_lower": 142.89,
    "price_vs_sma20_pct": 5.2,
    "price_vs_sma50_pct": 6.5,
    "volume_ratio": 0.83
  },
  "fundamentals": {
    "market_cap": 299997003776,
    "pe_ratio": 20.941631,
    "forward_pe": 13.486866,
    "price_to_book": 1.5792183,
    "price_to_sales": 1.5899187,
    "profit_margin": 6.77,
    "operating_margin": 9.85,
    "roe": 7.32,
    "roa": 4.05,
    "revenue_growth": -1.4,
    "earnings_growth": -26.6,
    "debt_to_equity": 21.239,
    "current_ratio": 1.152,
    "quick_ratio": 0.72,
    "dividend_yield": 456.0,
    "fifty_two_week_high": 168.96,
    "fifty_two_week_low": 132.04,
    "fifty_day_avg": 153.433,
    "two_hundred_day_avg": 150.73015,
    "analyst_target": 172.66667,
    "analyst_recommendation": "buy",
    "num_analysts": 24,
    "sector": "Energy",
    "industry": "Oil & Gas Integrated",
    "pct_from_52w_high": -11.88,
    "pct_from_52w_low": 12.77
  },
  "macro": {
    "spy": {
      "price": 572.18,
      "change_1d_pct": 0.24,
      "change_7d_pct": 1.77
    },
    "vix": {
      "level": 17.15,
      "signal": "NORMAL"
    },
    "treasury_10y": {
      "yield_pct": 4.31
    },
    "dollar_index": {
      "level": 104.18
    },
    "gold": {
      "price": 3023.7
    },
    "regime": "BULL_NORMAL"
  },
  "news": [
    {
      "headline": "Jim Cramer Prefers Chevron (CVX) Over ExxonMobil \u2013 Here\u2019s Why",
      "source": "Yahoo",
      "datetime": 1742934518,
      "summary": "We recently published a list of 10 Stocks on Jim Cramer\u2019s Radar Amid Market Volatility. In this article, we are going to take a look at where Chevron Corp (NYSE:CVX) stands against other stocks on Jim Cramer\u2019s radar amid market volatility. Jim Cramer in a latest program on CNBC commented on the reas",
      "url": "https://finnhub.io/api/news?id=31ac784325f20ff1b3ce04ee502a54fb9cd99303761a019a3c3c0654efd509cc"
    },
    {
      "headline": "Oil loading slows at Venezuela's ports amid US tariffs, license termination, data shows",
      "source": "Finnhub",
      "datetime": 1742911383,
      "summary": "Loading of Venezuela's heavy crude at its main oil ports slowed this week after the administration of U.S. President Donald Trump published an executive order imposing a 25% tariff on trade with...",
      "url": "https://finnhub.io/api/news?id=52b4f89f08a497d6a9ab9501225b53cb266dd46ddcbeccfc18bbbde363e38a5c"
    },
    {
      "headline": "Shell Confirms Potential Sales of Chemicals Assets",
      "source": "Yahoo",
      "datetime": 1742895547,
      "summary": "Shell signaled the possible sale of its least parts of its chemicals business, as it seeks to bolster its share price and close the valuation gap with U.S. rivals such as Exxon and Chevron. The oil-and-gas major said Tuesday that it will explore strategic and partnership opportunities for its chemic",
      "url": "https://finnhub.io/api/news?id=a136f3e5a21197173ddd1611c78bbe7e96effc4d8330165fdfb8131e508cb67b"
    },
    {
      "headline": "Trump Tariff Uncertainty Will Break This Stock Market Calm, Brace for Another Storm. And 5 Other Things to Know Today.",
      "source": "MarketWatch",
      "datetime": 1742885760,
      "summary": "Trump Tariff Uncertainty Will Break This Stock Market Calm, Brace for Another Storm. And 5 Other Things to Know Today.",
      "url": "https://finnhub.io/api/news?id=6ca06b2027558d3e1f44e3d90106f5b4bfab7293b388a314d0bb3dde07cd4380"
    },
    {
      "headline": "Trump Might Exempt Some Nations From Reciprocal Tariffs",
      "source": "Yahoo",
      "datetime": 1742858880,
      "summary": "Levies on foreign goods including lumber and pharmaceuticals could come after April 2, president says.",
      "url": "https://finnhub.io/api/news?id=d4e5eb5f7ac487fbd9b0fe889f8e52b0faf1f3d0cf9bd6ee3aa440174ba17379"
    }
  ],
  "news_count": 5,
  "sec_filings": [
    {
      "form": "8-K",
      "date": "2025-03-17",
      "description": "eh250599067_8k.htm",
      "url": "https://www.sec.gov/Archives/edgar/data/93410/000095014225000756/eh250599067_8k.htm"
    },
    {
      "form": "4",
      "date": "2025-03-05",
      "description": "xslF345X05/form4.xml",
      "url": "https://www.sec.gov/Archives/edgar/data/93410/000112760225008377/xslF345X05/form4.xml"
    },
    {
      "form": "4",
      "date": "2025-03-05",
      "description": "xslF345X05/form4.xml",
      "url": "https://www.sec.gov/Archives/edgar/data/93410/000112760225008376/xslF345X05/form4.xml"
    },
    {
      "form": "4",
      "date": "2025-03-05",
      "description": "xslF345X05/form4.xml",
      "url": "https://www.sec.gov/Archives/edgar/data/93410/000112760225008375/xslF345X05/form4.xml"
    },
    {
      "form": "4",
      "date": "2025-02-27",
      "description": "xslF345X05/form4.xml",
      "url": "https://www.sec.gov/Archives/edgar/data/93410/000112760225007119/xslF345X05/form4.xml"
    }
  ],
  "sec_filings_count": 5,
  "data_quality": {
    "has_price": true,
    "has_technicals": true,
    "has_fundamentals": true,
    "has_macro": true,
    "has_news": true,
    "has_sec_filings": true
  }
}