{
  "ticker": "MSFT",
  "target_date": "2025-02-07",
  "actual_date": "2025-02-07",
  "collected_at": "2025-12-08T11:22:42.178424",
  "price": {
    "open": 413.43,
    "high": 415.58,
    "low": 405.11,
    "close": 406.7494812011719,
    "volume": 22886800,
    "change_1d_pct": -1.46,
    "change_7d_pct": -7.37,
    "change_30d_pct": -5.86
  },
  "technicals": {
    "rsi_14": 39.4,
    "sma_20": 422.56,
    "sma_50": 427.86,
    "macd": -4.61,
    "macd_signal": -2.166,
    "macd_histogram": -2.443,
    "bb_upper": 449.06,
    "bb_lower": 396.06,
    "price_vs_sma20_pct": -3.74,
    "price_vs_sma50_pct": -4.93,
    "volume_ratio": 0.96
  },
  "fundamentals": {
    "market_cap": 3657006317568,
    "pe_ratio": 34.991817,
    "forward_pe": 32.908695,
    "price_to_book": 10.073402,
    "price_to_sales": 12.446755,
    "profit_margin": 35.71,
    "operating_margin": 48.87,
    "roe": 32.24,
    "roa": 14.66,
    "revenue_growth": 18.4,
    "earnings_growth": 12.7,
    "debt_to_equity": 33.154,
    "current_ratio": 1.401,
    "quick_ratio": 1.254,
    "dividend_yield": 75.0,
    "fifty_two_week_high": 555.45,
    "fifty_two_week_low": 344.79,
    "fifty_day_avg": 507.7866,
    "two_hundred_day_avg": 469.7925,
    "analyst_target": 625.4096,
    "analyst_recommendation": "strong_buy",
    "num_analysts": 52,
    "sector": "Technology",
    "industry": "Software - Infrastructure",
    "pct_from_52w_high": -11.43,
    "pct_from_52w_low": 42.69
  },
  "macro": {
    "spy": {
      "price": 595.55,
      "change_1d_pct": -0.92,
      "change_7d_pct": -0.71
    },
    "vix": {
      "level": 16.54,
      "signal": "NORMAL"
    },
    "treasury_10y": {
      "yield_pct": 4.49
    },
    "dollar_index": {
      "level": 108.04
    },
    "gold": {
      "price": 2867.3
    },
    "regime": "BEAR_NORMAL"
  },
  "news": [
    {
      "headline": "Q4 '24 S&P 500 Earnings Strong (Except Tech); Now Seeing Negative Revisions To 2025 Estimates",
      "source": "SeekingAlpha",
      "datetime": 1738953600,
      "summary": "The forward 4-quarter S&P 500 EPS estimate fell to $271.24 this week, after last week\u00e2\u0080\u0099s $273.33 and the prior week\u00e2\u0080\u0099s $273.17.",
      "url": "https://finnhub.io/api/news?id=ae9f9b99c3c6a599e9e3c0718c7d606e96c40221bffffbe49227513d32636848"
    },
    {
      "headline": "Credo Technology: A 'Meh' Product In A 'Wow' Market",
      "source": "SeekingAlpha",
      "datetime": 1738949750,
      "summary": "Financial writer analyzes Credo Technology Group Holding Ltd's rise in AI despite its traditional product, benefiting from market timing. Click for more on CRDO.",
      "url": "https://finnhub.io/api/news?id=4a651478e533d71f36c8a428ac743905cf617bbe66c22a3afee303f80914f04b"
    },
    {
      "headline": "Our Real-Life Market-Beating U.S. Stock Portfolio, Ten Years After",
      "source": "SeekingAlpha",
      "datetime": 1738941899,
      "summary": "Discover the successful decade-long journey of a stock portfolio focusing on dividend growth companies, outperforming the S&P 500. Find out the lessons I've learned.",
      "url": "https://finnhub.io/api/news?id=69f2a2e36c559dc8a5ba8421ea4d629cea0d563ff75586bece98c0c1b4299a32"
    },
    {
      "headline": "Big Tech stocks drop sharply, weighing on S&P 500\u2019s attempt at weekly gain",
      "source": "MarketWatch",
      "datetime": 1738936323,
      "summary": "Big Tech stocks drop sharply, weighing on S&P 500\u2019s attempt at weekly gain",
      "url": "https://finnhub.io/api/news?id=a54a9d45e985badd3d293ff5006d137092cff567dad1d1f9c300e742a8322434"
    },
    {
      "headline": "The Mag 7\u2019s Strength Just Became a Weakness",
      "source": "MarketWatch",
      "datetime": 1738931400,
      "summary": "The Mag 7\u2019s Strength Just Became a Weakness",
      "url": "https://finnhub.io/api/news?id=ab1db9a348727135e4c6fcb7bcf5df3644d05333b6cfed28156d49e31adc5af9"
    }
  ],
  "news_count": 5,
  "sec_filings": [
    {
      "form": "4",
      "date": "2025-02-03",
      "description": "xslF345X05/form4.xml",
      "url": "https://www.sec.gov/Archives/edgar/data/789019/000106299325001527/xslF345X05/form4.xml"
    },
    {
      "form": "4",
      "date": "2025-02-03",
      "description": "xslF345X05/form4.xml",
      "url": "https://www.sec.gov/Archives/edgar/data/789019/000106299325001526/xslF345X05/form4.xml"
    },
    {
      "form": "4",
      "date": "2025-02-03",
      "description": "xslF345X05/form4.xml",
      "url": "https://www.sec.gov/Archives/edgar/data/789019/000106299325001525/xslF345X05/form4.xml"
    },
    {
      "form": "4",
      "date": "2025-02-03",
      "description": "xslF345X05/form4.xml",
      "url": "https://www.sec.gov/Archives/edgar/data/789019/000106299325001524/xslF345X05/form4.xml"
    },
    {
      "form": "4",
      "date": "2025-02-03",
      "description": "xslF345X05/form4.xml",
      "url": "https://www.sec.gov/Archives/edgar/data/789019/000106299325001523/xslF345X05/form4.xml"
    }
  ],
  "sec_filings_count": 5,
  "data_quality": {
    "has_price": true,
    "has_technicals": true,
    "has_fundamentals": true,
    "has_macro": true,
    "has_news": true,
    "has_sec_filings": true
  }
}