{
  "ticker": "WMT",
  "target_date": "2025-02-20",
  "actual_date": "2025-02-20",
  "collected_at": "2025-12-08T11:26:01.132538",
  "price": {
    "open": 98.04,
    "high": 99.37,
    "low": 95.96,
    "close": 96.48460388183594,
    "volume": 55450900,
    "change_1d_pct": -6.53,
    "change_7d_pct": -5.55,
    "change_30d_pct": 6.32
  },
  "technicals": {
    "rsi_14": 46.39,
    "sma_20": 99.62,
    "sma_50": 94.94,
    "macd": 2.196,
    "macd_signal": 2.525,
    "macd_histogram": -0.329,
    "bb_upper": 106.26,
    "bb_lower": 92.98,
    "price_vs_sma20_pct": -3.15,
    "price_vs_sma50_pct": 1.63,
    "volume_ratio": 3.26
  },
  "fundamentals": {
    "market_cap": 899497066496,
    "pe_ratio": 39.585968,
    "forward_pe": 41.47794,
    "price_to_book": 9.359549,
    "price_to_sales": 1.2794012,
    "profit_margin": 3.26,
    "operating_margin": 3.73,
    "roe": 23.66,
    "roa": 6.54,
    "revenue_growth": 5.8,
    "earnings_growth": 35.2,
    "debt_to_equity": 66.747,
    "current_ratio": 0.803,
    "quick_ratio": 0.196,
    "dividend_yield": 82.0,
    "fifty_two_week_high": 116.27,
    "fifty_two_week_low": 79.81,
    "fifty_day_avg": 104.9452,
    "two_hundred_day_avg": 98.23185,
    "analyst_target": 118.78947,
    "analyst_recommendation": "strong_buy",
    "num_analysts": 38,
    "sector": "Consumer Defensive",
    "industry": "Discount Stores",
    "pct_from_52w_high": -2.97,
    "pct_from_52w_low": 41.36
  },
  "macro": {
    "spy": {
      "price": 605.08,
      "change_1d_pct": -0.42,
      "change_7d_pct": 0.84
    },
    "vix": {
      "level": 15.66,
      "signal": "NORMAL"
    },
    "treasury_10y": {
      "yield_pct": 4.5
    },
    "dollar_index": {
      "level": 106.34
    },
    "gold": {
      "price": 2940.0
    },
    "regime": "BULL_NORMAL"
  },
  "news": [
    {
      "headline": "Stock market today: Asia shares trade mixed as China benchmarks surge while others slip",
      "source": "Finnhub",
      "datetime": 1740092466,
      "summary": "TOKYO \u2014 Asian shares were mixed Friday after a sharp slide for Walmart helped pull Wall Street off record highs. In Japan, where investors were watching currency swings, the benchmark Nikkei 225...",
      "url": "https://finnhub.io/api/news?id=d7800ac33f1233c685e9150cb68e4b24072ae324c3654abb68b2b728a421a68a"
    },
    {
      "headline": "Walmart : Transcript Management Call (Transcript Management Call FY 2025)",
      "source": "Finnhub",
      "datetime": 1740082884,
      "summary": "Corrected Transcript 20-Feb-2025 Walmart, Inc. Q4 2025 Earnings Call ...",
      "url": "https://finnhub.io/api/news?id=9cb111f02785f3d2d43fbaf9829b083b9f1bac76c10db3adfb305a69abddf5fd"
    },
    {
      "headline": "Consumer Cos Down After Walmart Outlook -- Consumer Roundup",
      "source": "MarketWatch",
      "datetime": 1740075240,
      "summary": "Consumer Cos Down After Walmart Outlook -- Consumer Roundup",
      "url": "https://finnhub.io/api/news?id=8217e91c749dad1d0603c8c85136bd611b226a7a1235aa7b4b8c70051bd96a76"
    },
    {
      "headline": "Designer Brands: Cheap, But With Several Caveats",
      "source": "SeekingAlpha",
      "datetime": 1740073292,
      "summary": "Designer Brands shares plummeted over 50% post disappointing Q1 results, driven by weak consumer spending and poor boot sales. Click to read why DBI is a Hold.",
      "url": "https://finnhub.io/api/news?id=33e17d52cd85976db5e3396cbd473270ceb9281d9a1dde8426dd6c1e300e7e43"
    },
    {
      "headline": "Stock Market Today: Nasdaq Hammered, Dow Jones Falls On Walmart Outlook; Alibaba Sparks Other China Stocks (Live Coverage)",
      "source": "DowJones",
      "datetime": 1740049669,
      "summary": "Stock Market Today: Nasdaq Hammered, Dow Jones Falls On Walmart Outlook; Alibaba Sparks Other China Stocks (Live Coverage)",
      "url": "https://finnhub.io/api/news?id=69409de546ecdb94ec0e587e6ed99fecd9c894824b091417153c96a89d90dfd7"
    }
  ],
  "news_count": 5,
  "sec_filings": [
    {
      "form": "4",
      "date": "2025-02-20",
      "description": "xslF345X05/form4.xml",
      "url": "https://www.sec.gov/Archives/edgar/data/104169/000112760225006050/xslF345X05/form4.xml"
    },
    {
      "form": "8-K",
      "date": "2025-02-20",
      "description": "wmt-20250220.htm",
      "url": "https://www.sec.gov/Archives/edgar/data/104169/000010416925000010/wmt-20250220.htm"
    },
    {
      "form": "13F-HR",
      "date": "2025-02-14",
      "description": "xslForm13F_X02/primary_doc.xml",
      "url": "https://www.sec.gov/Archives/edgar/data/104169/000112329225000099/xslForm13F_X02/primary_doc.xml"
    },
    {
      "form": "4",
      "date": "2025-02-13",
      "description": "xslF345X05/form4.xml",
      "url": "https://www.sec.gov/Archives/edgar/data/104169/000112760225004671/xslF345X05/form4.xml"
    },
    {
      "form": "4",
      "date": "2025-02-13",
      "description": "xslF345X05/form4.xml",
      "url": "https://www.sec.gov/Archives/edgar/data/104169/000112760225004668/xslF345X05/form4.xml"
    }
  ],
  "sec_filings_count": 5,
  "data_quality": {
    "has_price": true,
    "has_technicals": true,
    "has_fundamentals": true,
    "has_macro": true,
    "has_news": true,
    "has_sec_filings": true
  }
}