{
  "ticker": "JNJ",
  "date": "2025-04-10",
  "analysis_date": "2025-04-10",
  "sample_number": 22,
  "actual_day_number": 64,
  "portfolio_size": 100000,
  "market_data": {
    "actual_day": 64,
    "date": "2025-04-10",
    "open": 147.07,
    "close": 145.43,
    "high": 147.88,
    "low": 141.95,
    "volume": 13830500,
    "daily_return": -0.0112,
    "sample_num": 22
  },
  "timestamp": "2025-12-01T10:42:42.713522",
  "files_saved": 10,
  "path": "workflows\\JNJ\\2025-04-10_sample022_day064\\portfolio_100000",
  "historical_mode": true,
  "decision": {
    "verdict": "APPROVE",
    "position": 5930.43,
    "confidence": "LOW"
  }
}