{
  "ticker": "LLY",
  "target_date": "2025-10-03",
  "actual_date": "2025-10-03",
  "collected_at": "2025-12-08T12:21:46.425052",
  "price": {
    "open": 823.73,
    "high": 846.89,
    "low": 814.9,
    "close": 838.6383666992188,
    "volume": 5088500,
    "change_1d_pct": 2.44,
    "change_7d_pct": 13.21,
    "change_30d_pct": 18.32
  },
  "technicals": {
    "rsi_14": 71.36,
    "sma_20": 758.94,
    "sma_50": 734.79,
    "macd": 18.147,
    "macd_signal": 8.848,
    "macd_histogram": 9.299,
    "bb_upper": 823.83,
    "bb_lower": 694.05,
    "price_vs_sma20_pct": 10.5,
    "price_vs_sma50_pct": 14.13,
    "volume_ratio": 1.26
  },
  "fundamentals": {
    "market_cap": 892440674304,
    "pe_ratio": 48.776093,
    "forward_pe": 43.932922,
    "price_to_book": 37.48193,
    "price_to_sales": 15.019247,
    "profit_margin": 30.99,
    "operating_margin": 48.29,
    "roe": 96.47,
    "roa": 17.6,
    "revenue_growth": 53.9,
    "earnings_growth": 480.4,
    "debt_to_equity": 178.516,
    "current_ratio": 1.546,
    "quick_ratio": 0.724,
    "dividend_yield": 59.0,
    "fifty_two_week_high": 1111.99,
    "fifty_two_week_low": 623.78,
    "fifty_day_avg": 911.5326,
    "two_hundred_day_avg": 811.9354,
    "analyst_target": 1056.7045,
    "analyst_recommendation": "buy",
    "num_analysts": 27,
    "sector": "Healthcare",
    "industry": "Drug Manufacturers - General",
    "pct_from_52w_high": -10.47,
    "pct_from_52w_low": 59.59
  },
  "macro": {
    "spy": {
      "price": 669.21,
      "change_1d_pct": -0.0,
      "change_7d_pct": 1.7
    },
    "vix": {
      "level": 16.65,
      "signal": "NORMAL"
    },
    "treasury_10y": {
      "yield_pct": 4.12
    },
    "dollar_index": {
      "level": 97.72
    },
    "gold": {
      "price": 3880.8
    },
    "regime": "BULL_NORMAL"
  },
  "news": [
    {
      "headline": "Eli Lilly (LLY) Laps the Stock Market: Here's Why",
      "source": "Yahoo",
      "datetime": 1759527903,
      "summary": "Eli Lilly (LLY) closed the most recent trading day at $839.87, moving +2.44% from the previous trading session.",
      "url": "https://finnhub.io/api/news?id=97ef74947bab0695be2d8ea1d58ba846b3f5922ff9c62bd4fc83d464414f5a37"
    },
    {
      "headline": "US Equity Indexes Rise This Week as AI-Trade Lifts Tech, Healthcare Gains Following Pfizer Deal",
      "source": "Yahoo",
      "datetime": 1759525126,
      "summary": "US equity indexes ended higher this week as a federal government shutdown in its early days failed t",
      "url": "https://finnhub.io/api/news?id=6b62ac183b5a695c26807571dc66235f3c095bc9b6f389696fe9ff0940d3a2c8"
    },
    {
      "headline": "5 Large Cap Drug Stocks: Values or Traps?",
      "source": "Yahoo",
      "datetime": 1759524900,
      "summary": "Some drug stocks are cheap but is it another fake out?",
      "url": "https://finnhub.io/api/news?id=6b37ae979ad1261a96d773275c84229ccfdaabe06d40dae948855552f983204c"
    },
    {
      "headline": "Eli Lilly & Co. stock outperforms competitors on strong trading day",
      "source": "MarketWatch",
      "datetime": 1759509060,
      "summary": "Eli Lilly & Co. stock outperforms competitors on strong trading day",
      "url": "https://finnhub.io/api/news?id=540e9abd57b65034fc0f4f506206ebdfa28ec83fb6b12c5c4c8c148aadbad882"
    },
    {
      "headline": "Pharmaceutical Stocks: Valuations And Pipelines Are Only Beginning To Be Appreciated",
      "source": "SeekingAlpha",
      "datetime": 1759508459,
      "summary": "Discover why drug stocks like LLY, NVO, AZN & PFE could outperform in 2025 amid strong healthcare trends. Click for my picks.",
      "url": "https://finnhub.io/api/news?id=39054aec8ba10e961ea96a273ddee36fc4c99bf71a99023c0844a605f6cc98ae"
    }
  ],
  "news_count": 5,
  "sec_filings": [
    {
      "form": "4",
      "date": "2025-10-03",
      "description": "xslF345X05/form4-10032025_041001.xml",
      "url": "https://www.sec.gov/Archives/edgar/data/59478/000031601125000021/xslF345X05/form4-10032025_041001.xml"
    },
    {
      "form": "4",
      "date": "2025-10-02",
      "description": "xslF345X05/form4-10022025_081019.xml",
      "url": "https://www.sec.gov/Archives/edgar/data/59478/000031601125000019/xslF345X05/form4-10022025_081019.xml"
    },
    {
      "form": "4",
      "date": "2025-10-02",
      "description": "xslF345X05/form4-10022025_081016.xml",
      "url": "https://www.sec.gov/Archives/edgar/data/59478/000031601125000018/xslF345X05/form4-10022025_081016.xml"
    },
    {
      "form": "4",
      "date": "2025-10-01",
      "description": "xslF345X05/form4-10012025_041001.xml",
      "url": "https://www.sec.gov/Archives/edgar/data/59478/000031601125000011/xslF345X05/form4-10012025_041001.xml"
    },
    {
      "form": "4",
      "date": "2025-09-22",
      "description": "xslF345X05/form4-09222025_040901.xml",
      "url": "https://www.sec.gov/Archives/edgar/data/59478/000031601125000009/xslF345X05/form4-09222025_040901.xml"
    }
  ],
  "sec_filings_count": 5,
  "data_quality": {
    "has_price": true,
    "has_technicals": true,
    "has_fundamentals": true,
    "has_macro": true,
    "has_news": true,
    "has_sec_filings": true
  }
}