{
  "ticker": "GS",
  "target_date": "2025-05-19",
  "actual_date": "2025-05-19",
  "collected_at": "2025-12-08T11:46:50.621612",
  "price": {
    "open": 599.97,
    "high": 610.0,
    "low": 589.28,
    "close": 603.0294189453125,
    "volume": 2842100,
    "change_1d_pct": -1.09,
    "change_7d_pct": 8.24,
    "change_30d_pct": 30.05
  },
  "technicals": {
    "rsi_14": 78.03,
    "sma_20": 558.91,
    "sma_50": 536.47,
    "macd": 20.26,
    "macd_signal": 13.19,
    "macd_histogram": 7.071,
    "bb_upper": 618.8,
    "bb_lower": 499.01,
    "price_vs_sma20_pct": 7.89,
    "price_vs_sma50_pct": 12.41,
    "volume_ratio": 1.2
  },
  "fundamentals": {
    "market_cap": 261555568640,
    "pe_ratio": 17.554144,
    "forward_pe": 20.789581,
    "price_to_book": 2.482666,
    "price_to_sales": 4.561724,
    "profit_margin": 29.07,
    "operating_margin": 37.2,
    "roe": 13.53,
    "roa": 0.94,
    "revenue_growth": 20.7,
    "earnings_growth": 45.8,
    "debt_to_equity": 586.142,
    "current_ratio": 1.657,
    "quick_ratio": 1.49,
    "dividend_yield": 187.0,
    "fifty_two_week_high": 870.56,
    "fifty_two_week_low": 439.38,
    "fifty_day_avg": 790.1522,
    "two_hundred_day_avg": 679.5925,
    "analyst_target": 802.5263,
    "analyst_recommendation": "hold",
    "num_analysts": 19,
    "sector": "Financial Services",
    "industry": "Capital Markets",
    "pct_from_52w_high": -0.75,
    "pct_from_52w_low": 96.64
  },
  "macro": {
    "spy": {
      "price": 591.46,
      "change_1d_pct": 0.11,
      "change_7d_pct": 5.41
    },
    "vix": {
      "level": 18.14,
      "signal": "NORMAL"
    },
    "treasury_10y": {
      "yield_pct": 4.47
    },
    "dollar_index": {
      "level": 100.43
    },
    "gold": {
      "price": 3228.9
    },
    "regime": "BULL_NORMAL"
  },
  "news": [
    {
      "headline": "Goldman Sachs Group Inc. stock underperforms Monday when compared to competitors",
      "source": "MarketWatch",
      "datetime": 1747672440,
      "summary": "Goldman Sachs Group Inc. stock underperforms Monday when compared to competitors",
      "url": "https://finnhub.io/api/news?id=645620ecbc57fb856fc661b73d9e8c3421151a1b9d13bf63746b7bce5ea8a025"
    },
    {
      "headline": "How investors can defensively position for whatever comes next",
      "source": "Yahoo",
      "datetime": 1747648809,
      "summary": "Markets (^GSPC,\u00a0^IXIC,\u00a0^DJI) are climbing, but some investors are shifting to a more defensive stance. Crossmark Global Investments CEO and CIO Bob Doll joins Wealth host Brad Smith to explain why he\u2019s favoring high cash flow and profitable names like Visa (V), Mastercard (MA), and Goldman Sachs (GS",
      "url": "https://finnhub.io/api/news?id=654cefd43cbc3dd584e0ecd4fcc49bd2c300b4e598f316ded5b701ae28e2040c"
    },
    {
      "headline": "Morgan Stanley\u2019s Wilson Says Buy US Stock Dips After Moody\u2019s Cut",
      "source": "Yahoo",
      "datetime": 1747647938,
      "summary": "(Bloomberg) -- Investors should buy any dips in US stocks fueled by Friday\u2019s credit rating cut, as the trade truce with China has reduced the odds of a recession, according to Morgan Stanley\u2019s Michael Wilson.Most Read from BloombergHow a Highway Became San Francisco\u2019s Newest ParkAmerica, \u2018Nation of ",
      "url": "https://finnhub.io/api/news?id=791b925e7cfc5aeb723dfbc1a5881e00f11b12725124c172075694ea2a8c7354"
    },
    {
      "headline": "Model Portfolio For Capital Appreciation: May 2025",
      "source": "SeekingAlpha",
      "datetime": 1747574749,
      "summary": "Discover a model portfolio of dividend-paying stocks & ETFs aimed to beat the S&P 500. Learn strategies for diversification & long-term growth. Click for more.",
      "url": "https://finnhub.io/api/news?id=29e68c6a874f383bf720d101b9bbdde6f819a96418934ffe8a8abff486120174"
    },
    {
      "headline": "Big Tech Goes From Stock Market\u2019s Safest Bet to Biggest Question",
      "source": "Yahoo",
      "datetime": 1747569607,
      "summary": "(Bloomberg) -- For most of the past decade, a handful of high-flying technology companies have pushed the US stock market to record highs and become cornerstones of investment portfolios. But that\u2019s collapsed this year.Most Read from BloombergHow a Highway Became San Francisco\u2019s Newest ParkAmerica, ",
      "url": "https://finnhub.io/api/news?id=3241e52d58c197c46f264e2441ba4e15b2b8bfc0784ce073df349ace29c59d9d"
    }
  ],
  "news_count": 5,
  "sec_filings": [
    {
      "form": "4",
      "date": "2025-05-15",
      "description": "xslF345X05/wk-form4_1747339449.xml",
      "url": "https://www.sec.gov/Archives/edgar/data/886982/000169370925000010/xslF345X05/wk-form4_1747339449.xml"
    },
    {
      "form": "13F-HR",
      "date": "2025-05-09",
      "description": "xslForm13F_X02/primary_doc.xml",
      "url": "https://www.sec.gov/Archives/edgar/data/886982/000076999325000253/xslForm13F_X02/primary_doc.xml"
    },
    {
      "form": "10-Q",
      "date": "2025-05-02",
      "description": "gs-20250331.htm",
      "url": "https://www.sec.gov/Archives/edgar/data/886982/000088698225000009/gs-20250331.htm"
    },
    {
      "form": "4",
      "date": "2025-05-02",
      "description": "xslF345X05/wk-form4_1746216606.xml",
      "url": "https://www.sec.gov/Archives/edgar/data/886982/000169370925000008/xslF345X05/wk-form4_1746216606.xml"
    },
    {
      "form": "4",
      "date": "2025-05-02",
      "description": "xslF345X05/wk-form4_1746216535.xml",
      "url": "https://www.sec.gov/Archives/edgar/data/886982/000175439925000006/xslF345X05/wk-form4_1746216535.xml"
    }
  ],
  "sec_filings_count": 5,
  "data_quality": {
    "has_price": true,
    "has_technicals": true,
    "has_fundamentals": true,
    "has_macro": true,
    "has_news": true,
    "has_sec_filings": true
  }
}